datastructure/Plot_Collections.py
datastructure/Plot_IDIADA.py
datastructure/__init__.py
datastructure/datainterface.py
datastructure/datalake.py
datastructure/dataobjects.py
datastructure/datapool.py
datastructure/lib_objects/__init__.py
datastructure/lib_objects/amedata_object.py
datastructure/lib_objects/amegp_object.py
datastructure/lib_objects/ameres_object.py
datastructure/lib_objects/asammdf_object.py
datastructure/lib_objects/data_object.py
datastructure/lib_objects/finance_object.py
datastructure/lib_objects/matlab_object.py
datastructure/lib_objects/mdf_object.py
datastructure/lib_objects/pandas_object.py
datasurfer/Plot_Collections.py
datasurfer/Plot_IDIADA.py
datasurfer/__init__.py
datasurfer/datainterface.py
datasurfer/datalake.py
datasurfer/datapool.py
datasurfer/datautils.py
datasurfer/lib_dlearn/__init__.py
datasurfer/lib_mlearn/__init__.py
datasurfer/lib_mlearn/clustering.py
datasurfer/lib_mlearn/preproc.py
datasurfer/lib_objects/__init__.py
datasurfer/lib_objects/amedata_object.py
datasurfer/lib_objects/amegp_object.py
datasurfer/lib_objects/ameparam_object.py
datasurfer/lib_objects/ameres_object.py
datasurfer/lib_objects/amevari_object.py
datasurfer/lib_objects/asammdf_object.py
datasurfer/lib_objects/data_object.py
datasurfer/lib_objects/femke_object.py
datasurfer/lib_objects/finance_object.py
datasurfer/lib_objects/hdf_object.py
datasurfer/lib_objects/json_object.py
datasurfer/lib_objects/matlab_object.py
datasurfer/lib_objects/mdf_object.py
datasurfer/lib_objects/multisheet_object.py
datasurfer/lib_objects/numpy_object.py
datasurfer/lib_objects/pandas_object.py
datasurfer/lib_objects/parquet_object.py
datasurfer/lib_objects/pdf_object.py
datasurfer/lib_objects/string_object.py
datasurfer/lib_objects/xkf_object.py
datasurfer/lib_office/__init__.py
datasurfer/lib_plots/__init__.py
datasurfer/lib_plots/plot_collection.py
datasurfer/lib_plots/plot_utils.py
datasurfer/lib_poolobjects/__init__.py
datasurfer/lib_poolobjects/amemultires_object.py
datasurfer-1.2.0.dist-info/AUTHORS.rst
datasurfer-1.2.0.dist-info/LICENSE
datasurfer-1.2.0.dist-info/METADATA
datasurfer-1.2.0.dist-info/WHEEL
datasurfer-1.2.0.dist-info/top_level.txt
datasurfer-1.2.0.dist-info/RECORD
