Metadata-Version: 2.1
Name: datasurfer
Version: 1.2.0
Summary: A Python package for data processing
Home-page: https://github.com/yuw1si/datasurfer
Author: Wei Yu
Author-email: yuwei2005@gmail.com
License: MIT license
Keywords: datasurfer
Classifier: Development Status :: 2 - Pre-Alpha
Classifier: Intended Audience :: Developers
Classifier: License :: OSI Approved :: MIT License
Classifier: Natural Language :: English
Classifier: Programming Language :: Python :: 3
Classifier: Programming Language :: Python :: 3.6
Classifier: Programming Language :: Python :: 3.7
Classifier: Programming Language :: Python :: 3.8
Requires-Python: >=3.6
License-File: LICENSE
License-File: AUTHORS.rst
